{"runType":"Matchmaker","buildVersion":{"number":"12923","platform":"WindowsPlayer"},"analyticsPlayerId":"Steam-76561198983806636","analyticsPlayerFriendlyName":"oriolgomez","id":"0016f276-8f49-42ea-bdfa-cd9c41c4a197","saveVersion":65,"score":0,"challengeId":"","pubsubChannel":"","pubsubPresenceTimeout":0,"pubsubPresenceInterval":0,"initiatorData":{"shareCode":"","analyticsPlayerId":"","analyticsPlayerFriendlyName":""},"startingConditions":{"seed":1129711205,"isBattleMode":false,"isFtueRun":false,"battleModeStartTime":"","battleModeTimerScalar":0.0,"battleWarmup":0,"version":"12923","mainClassInfo":{"className":"","classLevel":0,"championIndex":0,"random":false},"subclassInfo":{"className":"","classLevel":0,"championIndex":0,"random":false},"ascensionLevel":0,"spChallengeId":"","covenants":[],"mutators":[],"enabledDlcs":[]},"completedBattles":[],"blessings":[],"relicModifiedRules":{"towerHealingDisabled":false},"pregeneratedRelicRewards":[],"currentBranch":0,"deckState":[],"cachedDeckState":[],"mergedCardStates":[],"merchantGoodStates":[],"storyEventStates":[],"followupEventStates":[],"rewardStates":[],"runState":{"distance":-1,"nodes":[],"draftRarityBucketMainClass":{"_buckets":[],"_lastBucket":{"_rarities":[]}},"draftRarityBucketSubclass":{"_buckets":[],"_lastBucket":{"_rarities":[]}},"rewardSubBuckets":[]},"gameSequence":0,"maxTowerHP":{"_values":[204,87,36,14,230,43,242,63,161,110,199,103,80,183,83,64]},"towerHP":{"_values":[204,87,36,14,230,43,242,63,161,110,199,103,80,183,83,64]},"towerHPOverTime":[],"gold":{"_values":[191,109,173,145,223,182,230,63,73,74,185,129,36,165,72,64]},"goldOverTime":[],"hellforgedSaveData":{"crystals":{"_values":[0,0,0,0,0,0,0,0,0,0,0,0,0,0,0,0]}},"storyStateJson":"","storyRecord":{"_storySeenCount":[]},"eventCachedCard":{"cardDataID":"","cardModifiers":{"additionalDamage":0,"additionalMaxHP":0,"additionalCost":0,"additionalXCost":0,"additionalHeal":0,"additionalSize":0,"cardTraitReplacements":[],"cardUpgrades":[],"mergedCardStateIDs":[]}},"combatScore":0,"randomState":{"_rngStates":[{"rngIdName":"Master","rng":{"_seed":1129711205,"_state":{"s0":1768043342,"s1":-1061876281,"s2":-1925321647,"s3":2124146386}}},{"rngIdName":"NonDeterministic","rng":{"_seed":1421087136,"_state":{"s0":1421087136,"s1":-1009150943,"s2":-1375462906,"s3":397769311}}},{"rngIdName":"SetupRun","rng":{"_seed":1268957329,"_state":{"s0":1268957329,"s1":1614451254,"s2":383030607,"s3":787427116}}},{"rngIdName":"Spawning","rng":{"_seed":981637733,"_state":{"s0":981637733,"s1":-823527718,"s2":-1889595901,"s3":353706544}}},{"rngIdName":"Chatter","rng":{"_seed":258244827,"_state":{"s0":258244827,"s1":-979826328,"s2":-46047735,"s3":1146874510}}},{"rngIdName":"CardDraw","rng":{"_seed":2066235457,"_state":{"s0":2066235457,"s1":1326129830,"s2":528056703,"s3":-1883894244}}},{"rngIdName":"Battle","rng":{"_seed":651407869,"_state":{"s0":651407869,"s1":900767186,"s2":-1679710757,"s3":784704104}}},{"rngIdName":"BossActions","rng":{"_seed":137121528,"_state":{"s0":137121528,"s1":-1199185959,"s2":478900638,"s3":-1507630761}}},{"rngIdName":"Merchant","rng":{"_seed":602242424,"_state":{"s0":602242424,"s1":133675097,"s2":1288854558,"s3":253519319}}},{"rngIdName":"StoryEvents","rng":{"_seed":443941643,"_state":{"s0":443941643,"s1":1367152216,"s2":-742987591,"s3":-758918658}}},{"rngIdName":"Rewards","rng":{"_seed":554765800,"_state":{"s0":554765800,"s1":1837343881,"s2":-205767922,"s3":1782565511}}},{"rngIdName":"Trials","rng":{"_seed":1260444860,"_state":{"s0":1260444860,"s1":-1824804307,"s2":-467509054,"s3":-458883445}}},{"rngIdName":"PubSub","rng":{"_seed":1134960235,"_state":{"s0":1134960235,"s1":-1883356360,"s2":-24019687,"s3":1124580318}}},{"rngIdName":"BossGeneration","rng":{"_seed":1768043342,"_state":{"s0":1768043342,"s1":1884617671,"s2":-1565141884,"s3":1276949}}},{"rngIdName":"BattleTest","rng":{"_seed":1085607368,"_state":{"s0":1085607368,"s1":742815721,"s2":-1051197458,"s3":-953133337}}},{"rngIdName":"AutoselectTrainPath","rng":{"_seed":222162002,"_state":{"s0":222162002,"s1":1797529179,"s2":-772035352,"s3":573267849}}},{"rngIdName":"HellforgedShardEnemy","rng":{"_seed":2124146386,"_state":{"s0":2124146386,"s1":1237742299,"s2":-692092056,"s3":-1363574775}}}]},"runTime":0,"grantableCardRewards":[],"grantableRelicRewards":[],"grantableEnhancerRewards":[],"ssId":-30486685,"runStats":{"stats":[]},"battleModeRank":0,"dailyChallengeStartDate":"","relicRecords":[]}